setup.py
c_mssql/__init__.py
c_mssql/mssql_conn.py
c_mssql/mssql_dst.py
c_mssql/mssql_source.py
c_mssql/mssql_sql.py
c_mssql/setup.py
c_mssql.egg-info/PKG-INFO
c_mssql.egg-info/SOURCES.txt
c_mssql.egg-info/dependency_links.txt
c_mssql.egg-info/requires.txt
c_mssql.egg-info/top_level.txt