Metadata-Version: 2.1
Name: c-mssql
Version: 0.2.2
Summary: c_mssql
Home-page: https://www.cnblogs.com/Evan-fanfan/
Author: evanyang
Author-email: lightyiyi@qq.com
License: MIT tencent_message
Platform: UNKNOWN
